odoo/addons/project_task_material/README.rst
odoo/addons/project_task_material/__init__.py
odoo/addons/project_task_material/__manifest__.py
odoo/addons/project_task_material/i18n/am.po
odoo/addons/project_task_material/i18n/ar.po
odoo/addons/project_task_material/i18n/bg.po
odoo/addons/project_task_material/i18n/bs.po
odoo/addons/project_task_material/i18n/ca.po
odoo/addons/project_task_material/i18n/cs.po
odoo/addons/project_task_material/i18n/da.po
odoo/addons/project_task_material/i18n/de.po
odoo/addons/project_task_material/i18n/el.po
odoo/addons/project_task_material/i18n/el_GR.po
odoo/addons/project_task_material/i18n/en_GB.po
odoo/addons/project_task_material/i18n/es.po
odoo/addons/project_task_material/i18n/es_AR.po
odoo/addons/project_task_material/i18n/es_CL.po
odoo/addons/project_task_material/i18n/es_CO.po
odoo/addons/project_task_material/i18n/es_CR.po
odoo/addons/project_task_material/i18n/es_DO.po
odoo/addons/project_task_material/i18n/es_EC.po
odoo/addons/project_task_material/i18n/es_ES.po
odoo/addons/project_task_material/i18n/es_MX.po
odoo/addons/project_task_material/i18n/es_PE.po
odoo/addons/project_task_material/i18n/es_PY.po
odoo/addons/project_task_material/i18n/es_VE.po
odoo/addons/project_task_material/i18n/et.po
odoo/addons/project_task_material/i18n/eu.po
odoo/addons/project_task_material/i18n/fa.po
odoo/addons/project_task_material/i18n/fi.po
odoo/addons/project_task_material/i18n/fr.po
odoo/addons/project_task_material/i18n/fr_CA.po
odoo/addons/project_task_material/i18n/fr_CH.po
odoo/addons/project_task_material/i18n/fr_FR.po
odoo/addons/project_task_material/i18n/gl.po
odoo/addons/project_task_material/i18n/gl_ES.po
odoo/addons/project_task_material/i18n/he.po
odoo/addons/project_task_material/i18n/hr.po
odoo/addons/project_task_material/i18n/hr_HR.po
odoo/addons/project_task_material/i18n/hu.po
odoo/addons/project_task_material/i18n/id.po
odoo/addons/project_task_material/i18n/it.po
odoo/addons/project_task_material/i18n/ja.po
odoo_addon_project_task_material-18.0.1.0.0.2.dist-info/METADATA
odoo_addon_project_task_material-18.0.1.0.0.2.dist-info/WHEEL
odoo_addon_project_task_material-18.0.1.0.0.2.dist-info/top_level.txt
odoo_addon_project_task_material-18.0.1.0.0.2.dist-info/RECORD
